[
  { "player_id": "p1", "player_name": "Gregor Kobel", "profile_image_url": "https://via.placeholder.com/80", "avg_rating": 7.2, "position_sort_order": 10, "line_number": 5, "position_detail_name": "GK", "lineup_type": "STARTING", "is_captain": true, "substitution_status": "NONE", "substitution_partner_name": null, "yellow_cards": 0, "is_sent_off": false, "goals": 0, "assists": 0, "is_playing": true },
  { "player_id": "p2", "player_name": "Julian Ryerson", "profile_image_url": "https://via.placeholder.com/80", "avg_rating": 6.8, "position_sort_order": 50, "line_number": 4, "position_detail_name": "RB", "lineup_type": "STARTING", "is_captain": false, "substitution_status": "NONE", "substitution_partner_name": null, "yellow_cards": 0, "is_sent_off": false, "goals": 0, "assists": 0, "is_playing": true },
  { "player_id": "p3", "player_name": "Waldemar Anton", "profile_image_url": "https://via.placeholder.com/80", "avg_rating": 7.0, "position_sort_order": 40, "line_number": 4, "position_detail_name": "RCB", "lineup_type": "STARTING", "is_captain": false, "substitution_status": "NONE", "substitution_partner_name": null, "yellow_cards": 1, "is_sent_off": false, "goals": 0, "assists": 0, "is_playing": true },
  { "player_id": "p4", "player_name": "Nico Schlotterbeck", "profile_image_url": "https://via.placeholder.com/80", "avg_rating": 7.1, "position_sort_order": 20, "line_number": 4, "position_detail_name": "LCB", "lineup_type": "STARTING", "is_captain": false, "substitution_status": "NONE", "substitution_partner_name": null, "yellow_cards": 0, "is_sent_off": false, "goals": 0, "assists": 0, "is_playing": true },
  { "player_id": "p5", "player_name": "Ramy Bensebaini", "profile_image_url": "https://via.placeholder.com/80", "avg_rating": 6.5, "position_sort_order": 10, "line_number": 4, "position_detail_name": "LB", "lineup_type": "STARTING", "is_captain": false, "substitution_status": "SUBSTITUTED_OUT", "substitution_partner_name": "Daniel Svensson", "yellow_cards": 0, "is_sent_off": false, "goals": 0, "assists": 0, "is_playing": false },
  { "player_id": "p6", "player_name": "Emre Can", "profile_image_url": "https://via.placeholder.com/80", "avg_rating": 6.9, "position_sort_order": 30, "line_number": 3, "position_detail_name": "RDM", "lineup_type": "STARTING", "is_captain": false, "substitution_status": "NONE", "substitution_partner_name": null, "yellow_cards": 0, "is_sent_off": false, "goals": 0, "assists": 1, "is_playing": true },
  { "player_id": "p7", "player_name": "Felix Nmecha", "profile_image_url": "https://via.placeholder.com/80", "avg_rating": 7.3, "position_sort_order": 10, "line_number": 3, "position_detail_name": "LDM", "lineup_type": "STARTING", "is_captain": false, "substitution_status": "NONE", "substitution_partner_name": null, "yellow_cards": 0, "is_sent_off": false, "goals": 0, "assists": 0, "is_playing": true },
  { "player_id": "p8", "player_name": "Karim Adeyemi", "profile_image_url": "https://via.placeholder.com/80", "avg_rating": 7.8, "position_sort_order": 30, "line_number": 2, "position_detail_name": "RAM", "lineup_type": "STARTING", "is_captain": false, "substitution_status": "NONE", "substitution_partner_name": null, "yellow_cards": 0, "is_sent_off": false, "goals": 1, "assists": 0, "is_playing": true },
  { "player_id": "p9", "player_name": "Julian Brandt", "profile_image_url": "https://via.placeholder.com/80", "avg_rating": 8.0, "position_sort_order": 20, "line_number": 2, "position_detail_name": "CAM", "lineup_type": "STARTING", "is_captain": false, "substitution_status": "NONE", "substitution_partner_name": null, "yellow_cards": 0, "is_sent_off": false, "goals": 0, "assists": 2, "is_playing": true },
  { "player_id": "p10", "player_name": "Julian Duranville", "profile_image_url": "https://via.placeholder.com/80", "avg_rating": 7.5, "position_sort_order": 10, "line_number": 2, "position_detail_name": "LAM", "lineup_type": "STARTING", "is_captain": false, "substitution_status": "NONE", "substitution_partner_name": null, "yellow_cards": 0, "is_sent_off": false, "goals": 0, "assists": 0, "is_playing": true },
  { "player_id": "p11", "player_name": "Serhou Guirassy", "profile_image_url": "https://via.placeholder.com/80", "avg_rating": 8.5, "position_sort_order": 20, "line_number": 1, "position_detail_name": "ST", "lineup_type": "STARTING", "is_captain": false, "substitution_status": "NONE", "substitution_partner_name": null, "yellow_cards": 0, "is_sent_off": false, "goals": 2, "assists": 0, "is_playing": true },
  { "player_id": "p12", "player_name": "Daniel Svensson", "profile_image_url": "https://via.placeholder.com/80", "avg_rating": 6.7, "position_sort_order": 10, "line_number": 4, "position_detail_name": "LB", "lineup_type": "BENCH", "is_captain": false, "substitution_status": "SUBSTITUTED_IN", "substitution_partner_name": "Ramy Bensebaini", "yellow_cards": 0, "is_sent_off": false, "goals": 0, "assists": 0, "is_playing": true },
  { "player_id": "p13", "player_name": "Alexander Meyer", "profile_image_url": "https://via.placeholder.com/80", "avg_rating": 0, "position_sort_order": 10, "line_number": 5, "position_detail_name": "GK", "lineup_type": "BENCH", "is_captain": false, "substitution_status": "NONE", "substitution_partner_name": null, "yellow_cards": 0, "is_sent_off": false, "goals": 0, "assists": 0, "is_playing": false }
]
